readtome/__init__.py
readtome/cli.py
readtome/transcode.py
readtome/version.py
readtome-0.0.1.dist-info/LICENSE
readtome-0.0.1.dist-info/METADATA
readtome-0.0.1.dist-info/WHEEL
readtome-0.0.1.dist-info/entry_points.txt
readtome-0.0.1.dist-info/top_level.txt
readtome-0.0.1.dist-info/RECORD
