Metadata-Version: 2.1
Name: readtome
Version: 0.0.1
Summary: CLI to read code via text-to-speech
Home-page: https://github.com/jbwinters/readtome
Download-URL: https://github.com/jbwinters/readtome/archive/0.0.1.tar.gz
Author: Josh Winters
Author-email: josh@winters.codes
License: MIT
Classifier: Development Status :: 3 - Alpha
Classifier: Intended Audience :: Developers
Classifier: Topic :: Software Development :: Libraries
Classifier: License :: OSI Approved :: MIT License
Classifier: Programming Language :: Python :: 3.8
Requires-Python: >=0.0.1
License-File: LICENSE
Requires-Dist: click (<8,>=7.0)
